crdesigner/__init__.py
crdesigner/common/__init__.py
crdesigner/common/common_file_reader_writer.py
crdesigner/common/config/__init__.py
crdesigner/common/config/config_base.py
crdesigner/common/config/general_config.py
crdesigner/common/config/gui_config.py
crdesigner/common/config/lanelet2_config.py
crdesigner/common/config/opendrive_config.py
crdesigner/common/config/osm_config.py
crdesigner/common/config/settings_config.py
crdesigner/common/file_reader.py
crdesigner/common/file_writer.py
crdesigner/common/logging.py
crdesigner/map_conversion/__init__.py
crdesigner/map_conversion/common/__init__.py
crdesigner/map_conversion/common/conversion_lanelet.py
crdesigner/map_conversion/common/conversion_lanelet_network.py
crdesigner/map_conversion/common/geometry.py
crdesigner/map_conversion/common/utils.py
crdesigner/map_conversion/lanelet2/__init__.py
crdesigner/map_conversion/lanelet2/cr2lanelet.py
crdesigner/map_conversion/lanelet2/lanelet2.py
crdesigner/map_conversion/lanelet2/lanelet2_parser.py
crdesigner/map_conversion/lanelet2/lanelet2cr.py
crdesigner/map_conversion/map_conversion_interface.py
crdesigner/map_conversion/opendrive/__init__.py
crdesigner/map_conversion/opendrive/cr2odr/__init__.py
crdesigner/map_conversion/opendrive/cr2odr/converter.py
crdesigner/map_conversion/opendrive/cr2odr/elements/junction.py
crdesigner/map_conversion/opendrive/cr2odr/elements/light.py
crdesigner/map_conversion/opendrive/cr2odr/elements/obstacle.py
crdesigner/map_conversion/opendrive/cr2odr/elements/road.py
crdesigner/map_conversion/opendrive/cr2odr/elements/sign.py
crdesigner/map_conversion/opendrive/cr2odr/elements/signal.py
crdesigner/map_conversion/opendrive/cr2odr/elements/stop_line.py
crdesigner/map_conversion/opendrive/cr2odr/utils/commonroad_ccosy_geometry_util.py
crdesigner/map_conversion/opendrive/cr2odr/utils/config.py
crdesigner/map_conversion/opendrive/cr2odr/utils/file_writer.py
crdesigner/map_conversion/opendrive/odr2cr/__init__.py
commonroad_scenario_designer-0.8.5.dist-info/METADATA
commonroad_scenario_designer-0.8.5.dist-info/WHEEL
commonroad_scenario_designer-0.8.5.dist-info/entry_points.txt
commonroad_scenario_designer-0.8.5.dist-info/licenses/LICENSE.txt
commonroad_scenario_designer-0.8.5.dist-info/RECORD
