Metadata-Version: 2.4
Name: commonroad-scenario-designer
Version: 0.8.5
Summary: Toolbox for Map Conversion and Scenario Creation for Autonomous Vehicles
License: GPL-3.0
License-File: LICENSE.txt
Keywords: autonomous,automated,vehicles,driving,motion,planning,simulation,map,scenario
Author: Cyber-Physical Systems Group, Technical University of Munich
Author-email: commonroad@lists.lrz.de
Requires-Python: >=3.10,<3.14
Classifier: License :: OSI Approved :: GNU General Public License v3 (GPLv3)
Classifier: License :: OSI Approved :: GNU General Public License v3 or later (GPLv3+)
Classifier: Operating System :: POSIX :: Linux
Classifier: Programming Language :: Python :: 3
Classifier: Programming Language :: Python :: 3.10
Classifier: Programming Language :: Python :: 3.11
Classifier: Programming Language :: Python :: 3.12
Classifier: Programming Language :: Python :: 3.13
Requires-Dist: antlr4-python3-runtime (==4.9.3)
Requires-Dist: commonroad-clcs (>=2025.1)
Requires-Dist: commonroad-drivability-checker (>=2025.1,<2026.0)
Requires-Dist: commonroad-io (>=2024.2,<=2024.3)
Requires-Dist: commonroad-sumo (>=2025.1.3)
Requires-Dist: iso3166 (>=2.1.1,<3.0.0)
Requires-Dist: kdtree (>=0.16,<0.17)
Requires-Dist: lxml (>=6.0.2,<7.0.0)
Requires-Dist: matplotlib (>=3.6.0)
Requires-Dist: mercantile (>=1.2.1,<2.0.0)
Requires-Dist: mgrs (>=1.4.5)
Requires-Dist: networkx (>=3.0,<4.0)
Requires-Dist: numpy (>=1.26.1) ; python_version < "3.13"
Requires-Dist: numpy (>=2.1.0) ; python_version >= "3.13"
Requires-Dist: omegaconf (>=2.3.0,<3.0.0)
Requires-Dist: ordered-set (>=4.1.0,<5.0.0)
Requires-Dist: pandas (>=2.0.2,<3.0.0)
Requires-Dist: pyclothoids (>=0.1.5,<0.2.0)
Requires-Dist: pygeodesy (>=23.3.23,<24.0.0)
Requires-Dist: pymetis (>=2020.1)
Requires-Dist: pyproj (>=3.4.1,<4.0.0)
Requires-Dist: pyqt6 (>=6.6.0)
Requires-Dist: pyyaml (>=6.0,<7.0)
Requires-Dist: requests (>=2.31.0,<3.0.0)
Requires-Dist: scipy (>=1.11.3) ; python_version < "3.13"
Requires-Dist: scipy (>=1.13.0) ; python_version >= "3.13"
Requires-Dist: shapely (>=2.0.1)
Requires-Dist: similaritymeasures (>=0.4.4)
Requires-Dist: typer (>=0.9.0,<0.10.0)
Requires-Dist: typing-extensions (>=4.8.0,<5.0.0)
Requires-Dist: urllib3 (>=2.0.3,<3.0.0)
Requires-Dist: utm (>=0.7.0,<0.8.0)
Project-URL: Documentation, https://cps.pages.gitlab.lrz.de/commonroad/commonroad-scenario-designer/
Project-URL: Forum, https://github.com/CommonRoad/commonroad-scenario-designer/discussions
Project-URL: Homepage, https://commonroad.in.tum.de/tools/scenario-designer
Project-URL: Repository, https://github.com/CommonRoad/commonroad-scenario-designer
Project-URL: Source, https://github.com/CommonRoad/commonroad-scenario-designer
